[
  {
    "trend_arrow": "FLAT", 
    "display_time": "2016-07-24T00:09:11-07:00", 
    "noise": 1, 
    "system_time": "2016-07-24T06:59:17-07:00", 
    "direction": "Flat", 
    "sgv": 126, 
    "dateString": "2016-07-24T00:09:11-07:00", 
    "date": 1469344151000, 
    "unfiltered": 152096, 
    "filtered": 156000, 
    "device": "openaps://cgm", 
    "rssi": 451, 
    "type": "sgv", 
    "glucose": 126
  }, 
  {
    "trend_arrow": "FLAT", 
    "display_time": "2016-07-24T00:04:10-07:00", 
    "noise": 1, 
    "system_time": "2016-07-24T06:54:17-07:00", 
    "direction": "Flat", 
    "sgv": 130, 
    "dateString": "2016-07-24T00:04:10-07:00", 
    "date": 1469343850000, 
    "unfiltered": 155520, 
    "filtered": 156832, 
    "device": "openaps://cgm", 
    "rssi": 186, 
    "type": "sgv", 
    "glucose": 130
  }, 
  {
    "trend_arrow": "FLAT", 
    "display_time": "2016-07-24T00:24:11-07:00", 
    "noise": 1, 
    "system_time": "2016-07-24T07:14:17-07:00", 
    "direction": "Flat", 
    "sgv": 126, 
    "dateString": "2016-07-24T00:24:11-07:00", 
    "date": 1469345051000, 
    "unfiltered": 152096, 
    "filtered": 152448, 
    "device": "openaps://cgm", 
    "rssi": 450, 
    "type": "sgv", 
    "glucose": 126
  }, 
  {
    "trend_arrow": "FLAT", 
    "display_time": "2016-07-24T00:19:10-07:00", 
    "noise": 1, 
    "system_time": "2016-07-24T07:09:17-07:00", 
    "direction": "Flat", 
    "sgv": 127, 
    "dateString": "2016-07-24T00:19:10-07:00", 
    "date": 1469344750000, 
    "unfiltered": 153312, 
    "filtered": 153312, 
    "device": "openaps://cgm", 
    "rssi": 186, 
    "type": "sgv", 
    "glucose": 127
  }, 
  {
    "trend_arrow": "FLAT", 
    "display_time": "2016-07-24T00:34:11-07:00", 
    "noise": 1, 
    "system_time": "2016-07-24T07:24:17-07:00", 
    "direction": "Flat", 
    "sgv": 123, 
    "dateString": "2016-07-24T00:34:11-07:00", 
    "date": 1469345651000, 
    "unfiltered": 148832, 
    "filtered": 151488, 
    "device": "openaps://cgm", 
    "rssi": 450, 
    "type": "sgv", 
    "glucose": 123
  }, 
  {
    "trend_arrow": "FLAT", 
    "display_time": "2016-07-24T00:29:10-07:00", 
    "noise": 1, 
    "system_time": "2016-07-24T07:19:17-07:00", 
    "direction": "Flat", 
    "sgv": 124, 
    "dateString": "2016-07-24T00:29:10-07:00", 
    "date": 1469345350000, 
    "unfiltered": 150496, 
    "filtered": 152128, 
    "device": "openaps://cgm", 
    "rssi": 187, 
    "type": "sgv", 
    "glucose": 124
  }, 
  {
    "trend_arrow": "FLAT", 
    "display_time": "2016-07-24T01:04:11-07:00", 
    "noise": 1, 
    "system_time": "2016-07-24T07:54:17-07:00", 
    "direction": "Flat", 
    "sgv": 107, 
    "dateString": "2016-07-24T01:04:11-07:00", 
    "date": 1469347451000, 
    "unfiltered": 134144, 
    "filtered": 136288, 
    "device": "openaps://cgm", 
    "rssi": 441, 
    "type": "sgv", 
    "glucose": 107
  }, 
  {
    "trend_arrow": "FLAT", 
    "display_time": "2016-07-24T00:59:10-07:00", 
    "noise": 1, 
    "system_time": "2016-07-24T07:49:17-07:00", 
    "direction": "Flat", 
    "sgv": 108, 
    "dateString": "2016-07-24T00:59:10-07:00", 
    "date": 1469347150000, 
    "unfiltered": 135776, 
    "filtered": 138784, 
    "device": "openaps://cgm", 
    "rssi": 180, 
    "type": "sgv", 
    "glucose": 108
  }, 
  {
    "trend_arrow": "FLAT", 
    "display_time": "2016-07-24T01:44:11-07:00", 
    "noise": 1, 
    "system_time": "2016-07-24T08:34:17-07:00", 
    "direction": "Flat", 
    "sgv": 90, 
    "dateString": "2016-07-24T01:44:11-07:00", 
    "date": 1469349851000, 
    "unfiltered": 118816, 
    "filtered": 119440, 
    "device": "openaps://cgm", 
    "rssi": 443, 
    "type": "sgv", 
    "glucose": 90
  }, 
  {
    "trend_arrow": "FLAT", 
    "display_time": "2016-07-24T01:39:10-07:00", 
    "noise": 1, 
    "system_time": "2016-07-24T08:29:17-07:00", 
    "direction": "Flat", 
    "sgv": 91, 
    "dateString": "2016-07-24T01:39:10-07:00", 
    "date": 1469349550000, 
    "unfiltered": 119360, 
    "filtered": 121504, 
    "device": "openaps://cgm", 
    "rssi": 192, 
    "type": "sgv", 
    "glucose": 91
  }, 
  {
    "trend_arrow": "FLAT", 
    "display_time": "2016-07-24T04:29:09-07:00", 
    "noise": 1, 
    "system_time": "2016-07-24T11:19:16-07:00", 
    "direction": "Flat", 
    "sgv": 129, 
    "dateString": "2016-07-24T04:29:09-07:00", 
    "date": 1469359749000, 
    "unfiltered": 155104, 
    "filtered": 151872, 
    "device": "openaps://cgm", 
    "rssi": 187, 
    "type": "sgv", 
    "glucose": 129
  }, 
  {
    "trend_arrow": "FLAT", 
    "display_time": "2016-07-24T04:24:09-07:00", 
    "noise": 1, 
    "system_time": "2016-07-24T11:14:16-07:00", 
    "direction": "Flat", 
    "sgv": 128, 
    "dateString": "2016-07-24T04:24:09-07:00", 
    "date": 1469359449000, 
    "unfiltered": 153696, 
    "filtered": 151328, 
    "device": "openaps://cgm", 
    "rssi": 188, 
    "type": "sgv", 
    "glucose": 128
  }
]