[
  {
    "trend_arrow": "FLAT", 
    "display_time": "2016-07-19T14:49:24-07:00", 
    "noise": 1, 
    "system_time": "2016-07-19T20:45:05-07:00", 
    "direction": "Flat", 
    "sgv": 149, 
    "dateString": "2016-07-19T14:49:24-07:00", 
    "date": 1468964964000, 
    "unfiltered": 179232, 
    "filtered": 177248, 
    "device": "openaps://cgm", 
    "rssi": 699, 
    "type": "sgv", 
    "glucose": 149
  }, 
  {
    "trend_arrow": "FLAT", 
    "display_time": "2016-07-19T14:44:23-07:00", 
    "noise": 1, 
    "system_time": "2016-07-19T20:40:05-07:00", 
    "direction": "Flat", 
    "sgv": 149, 
    "dateString": "2016-07-19T14:44:23-07:00", 
    "date": 1468964663000, 
    "unfiltered": 178816, 
    "filtered": 174752, 
    "device": "openaps://cgm", 
    "rssi": 178, 
    "type": "sgv", 
    "glucose": 149
  }, 
  {
    "trend_arrow": "FLAT", 
    "display_time": "2016-07-19T16:59:23-07:00", 
    "noise": 1, 
    "system_time": "2016-07-19T22:55:04-07:00", 
    "direction": "Flat", 
    "sgv": 111, 
    "dateString": "2016-07-19T16:59:23-07:00", 
    "date": 1468972763000, 
    "unfiltered": 139904, 
    "filtered": 132928, 
    "device": "openaps://cgm", 
    "rssi": 195, 
    "type": "sgv", 
    "glucose": 111
  }, 
  {
    "trend_arrow": "FLAT", 
    "display_time": "2016-07-19T16:54:22-07:00", 
    "noise": 1, 
    "system_time": "2016-07-19T22:50:04-07:00", 
    "direction": "Flat", 
    "sgv": 108, 
    "dateString": "2016-07-19T16:54:22-07:00", 
    "date": 1468972462000, 
    "unfiltered": 136160, 
    "filtered": 130064, 
    "device": "openaps://cgm", 
    "rssi": 187, 
    "type": "sgv", 
    "glucose": 108
  }, 
  {
    "trend_arrow": "FLAT", 
    "display_time": "2016-07-19T17:09:23-07:00", 
    "noise": 1, 
    "system_time": "2016-07-19T23:05:04-07:00", 
    "direction": "Flat", 
    "sgv": 108, 
    "dateString": "2016-07-19T17:09:23-07:00", 
    "date": 1468973363000, 
    "unfiltered": 137184, 
    "filtered": 139200, 
    "device": "openaps://cgm", 
    "rssi": 181, 
    "type": "sgv", 
    "glucose": 108
  }, 
  {
    "trend_arrow": "FLAT", 
    "display_time": "2016-07-19T17:04:22-07:00", 
    "noise": 1, 
    "system_time": "2016-07-19T23:00:04-07:00", 
    "direction": "Flat", 
    "sgv": 111, 
    "dateString": "2016-07-19T17:04:22-07:00", 
    "date": 1468973062000, 
    "unfiltered": 139840, 
    "filtered": 136480, 
    "device": "openaps://cgm", 
    "rssi": 178, 
    "type": "sgv", 
    "glucose": 111
  }, 
  {
    "trend_arrow": "FLAT", 
    "display_time": "2016-07-19T17:49:22-07:00", 
    "noise": 1, 
    "system_time": "2016-07-19T23:45:04-07:00", 
    "direction": "Flat", 
    "sgv": 105, 
    "dateString": "2016-07-19T17:49:22-07:00", 
    "date": 1468975762000, 
    "unfiltered": 134336, 
    "filtered": 130752, 
    "device": "openaps://cgm", 
    "rssi": 192, 
    "type": "sgv", 
    "glucose": 105
  }, 
  {
    "trend_arrow": "FLAT", 
    "display_time": "2016-07-19T17:44:22-07:00", 
    "noise": 1, 
    "system_time": "2016-07-19T23:40:04-07:00", 
    "direction": "Flat", 
    "sgv": 103, 
    "dateString": "2016-07-19T17:44:22-07:00", 
    "date": 1468975462000, 
    "unfiltered": 132096, 
    "filtered": 128272, 
    "device": "openaps://cgm", 
    "rssi": 182, 
    "type": "sgv", 
    "glucose": 103
  }
]