[
  {
    "trend_arrow": "FLAT", 
    "display_time": "2016-07-18T21:34:27-07:00", 
    "noise": 1, 
    "system_time": "2016-07-19T03:30:08-07:00", 
    "direction": "Flat", 
    "sgv": 91, 
    "dateString": "2016-07-18T21:34:27-07:00", 
    "date": 1468902867000, 
    "unfiltered": 112288, 
    "filtered": 114464, 
    "device": "openaps://cgm", 
    "rssi": 449, 
    "type": "sgv", 
    "glucose": 91
  }, 
  {
    "trend_arrow": "FLAT", 
    "display_time": "2016-07-18T21:29:26-07:00", 
    "noise": 1, 
    "system_time": "2016-07-19T03:25:08-07:00", 
    "direction": "Flat", 
    "sgv": 91, 
    "dateString": "2016-07-18T21:29:26-07:00", 
    "date": 1468902566000, 
    "unfiltered": 112096, 
    "filtered": 119472, 
    "device": "openaps://cgm", 
    "rssi": 190, 
    "type": "sgv", 
    "glucose": 91
  }, 
  {
    "trend_arrow": "FLAT", 
    "display_time": "2016-07-18T22:14:27-07:00", 
    "noise": 1, 
    "system_time": "2016-07-19T04:10:08-07:00", 
    "direction": "Flat", 
    "sgv": 74, 
    "dateString": "2016-07-18T22:14:27-07:00", 
    "date": 1468905267000, 
    "unfiltered": 95920, 
    "filtered": 98176, 
    "device": "openaps://cgm", 
    "rssi": 448, 
    "type": "sgv", 
    "glucose": 74
  }, 
  {
    "trend_arrow": "FLAT", 
    "display_time": "2016-07-18T22:09:26-07:00", 
    "noise": 1, 
    "system_time": "2016-07-19T04:05:08-07:00", 
    "direction": "Flat", 
    "sgv": 77, 
    "dateString": "2016-07-18T22:09:26-07:00", 
    "date": 1468904966000, 
    "unfiltered": 98176, 
    "filtered": 101312, 
    "device": "openaps://cgm", 
    "rssi": 190, 
    "type": "sgv", 
    "glucose": 77
  }, 
  {
    "trend_arrow": "FLAT", 
    "display_time": "2016-07-18T22:34:27-07:00", 
    "noise": 1, 
    "system_time": "2016-07-19T04:30:08-07:00", 
    "direction": "Flat", 
    "sgv": 82, 
    "dateString": "2016-07-18T22:34:27-07:00", 
    "date": 1468906467000, 
    "unfiltered": 103696, 
    "filtered": 98816, 
    "device": "openaps://cgm", 
    "rssi": 450, 
    "type": "sgv", 
    "glucose": 82
  }, 
  {
    "trend_arrow": "FLAT", 
    "display_time": "2016-07-18T22:29:26-07:00", 
    "noise": 1, 
    "system_time": "2016-07-19T04:25:08-07:00", 
    "direction": "Flat", 
    "sgv": 79, 
    "dateString": "2016-07-18T22:29:26-07:00", 
    "date": 1468906166000, 
    "unfiltered": 100144, 
    "filtered": 96992, 
    "device": "openaps://cgm", 
    "rssi": 197, 
    "type": "sgv", 
    "glucose": 79
  }, 
  {
    "trend_arrow": "FLAT", 
    "display_time": "2016-07-18T22:44:27-07:00", 
    "noise": 1, 
    "system_time": "2016-07-19T04:40:08-07:00", 
    "direction": "Flat", 
    "sgv": 85, 
    "dateString": "2016-07-18T22:44:27-07:00", 
    "date": 1468907067000, 
    "unfiltered": 105728, 
    "filtered": 104160, 
    "device": "openaps://cgm", 
    "rssi": 446, 
    "type": "sgv", 
    "glucose": 85
  }, 
  {
    "trend_arrow": "FLAT", 
    "display_time": "2016-07-18T22:39:26-07:00", 
    "noise": 1, 
    "system_time": "2016-07-19T04:35:08-07:00", 
    "direction": "Flat", 
    "sgv": 85, 
    "dateString": "2016-07-18T22:39:26-07:00", 
    "date": 1468906766000, 
    "unfiltered": 106080, 
    "filtered": 101472, 
    "device": "openaps://cgm", 
    "rssi": 198, 
    "type": "sgv", 
    "glucose": 85
  }, 
  {
    "trend_arrow": "FLAT", 
    "display_time": "2016-07-18T23:14:26-07:00", 
    "noise": 1, 
    "system_time": "2016-07-19T05:10:08-07:00", 
    "direction": "Flat", 
    "sgv": 76, 
    "dateString": "2016-07-18T23:14:26-07:00", 
    "date": 1468908866000, 
    "unfiltered": 97168, 
    "filtered": 96912, 
    "device": "openaps://cgm", 
    "rssi": 193, 
    "type": "sgv", 
    "glucose": 76
  }, 
  {
    "trend_arrow": "FLAT", 
    "display_time": "2016-07-18T23:09:26-07:00", 
    "noise": 1, 
    "system_time": "2016-07-19T05:05:08-07:00", 
    "direction": "Flat", 
    "sgv": 78, 
    "dateString": "2016-07-18T23:09:26-07:00", 
    "date": 1468908566000, 
    "unfiltered": 99728, 
    "filtered": 97312, 
    "device": "openaps://cgm", 
    "rssi": 196, 
    "type": "sgv", 
    "glucose": 78
  }
]