[
  {
    "trend_arrow": "FLAT", 
    "system_time": "2016-07-27T09:09:01", 
    "noise": 1, 
    "direction": "Flat", 
    "sgv": 167, 
    "display_time": "2016-07-27T02:18:55", 
    "date": 1469611135000.0, 
    "dateString": "2016-07-27T02:18:55", 
    "unfiltered": 185920, 
    "filtered": 185216, 
    "device": "openaps://cgm", 
    "rssi": 195, 
    "type": "sgv", 
    "glucose": 167
  }, 
  {
    "trend_arrow": "FLAT", 
    "system_time": "2016-07-27T09:04:01", 
    "noise": 1, 
    "direction": "Flat", 
    "sgv": 165, 
    "display_time": "2016-07-27T02:13:55", 
    "date": 1469610835000.0, 
    "dateString": "2016-07-27T02:13:55", 
    "unfiltered": 184640, 
    "filtered": 185728, 
    "device": "openaps://cgm", 
    "rssi": 195, 
    "type": "sgv", 
    "glucose": 165
  }, 
  {
    "trend_arrow": "FLAT", 
    "system_time": "2016-07-27T08:59:01", 
    "noise": 1, 
    "direction": "Flat", 
    "sgv": 165, 
    "display_time": "2016-07-27T02:08:55", 
    "date": 1469610535000.0, 
    "dateString": "2016-07-27T02:08:55", 
    "unfiltered": 184768, 
    "filtered": 185792, 
    "device": "openaps://cgm", 
    "rssi": 192, 
    "type": "sgv", 
    "glucose": 165
  }, 
  {
    "trend_arrow": "FLAT", 
    "system_time": "2016-07-27T08:54:01", 
    "noise": 1, 
    "direction": "Flat", 
    "sgv": 166, 
    "display_time": "2016-07-27T02:03:55", 
    "date": 1469610235000.0, 
    "dateString": "2016-07-27T02:03:55", 
    "unfiltered": 185504, 
    "filtered": 184960, 
    "device": "openaps://cgm", 
    "rssi": 180, 
    "type": "sgv", 
    "glucose": 166
  }, 
  {
    "trend_arrow": "FLAT", 
    "system_time": "2016-07-27T08:49:01", 
    "noise": 1, 
    "direction": "Flat", 
    "sgv": 167, 
    "display_time": "2016-07-27T01:58:55", 
    "date": 1469609935000.0, 
    "dateString": "2016-07-27T01:58:55", 
    "unfiltered": 186272, 
    "filtered": 183552, 
    "device": "openaps://cgm", 
    "rssi": 197, 
    "type": "sgv", 
    "glucose": 167
  }, 
  {
    "trend_arrow": "FLAT", 
    "system_time": "2016-07-27T08:44:01", 
    "noise": 1, 
    "direction": "Flat", 
    "sgv": 165, 
    "display_time": "2016-07-27T01:53:55", 
    "date": 1469609635000.0, 
    "dateString": "2016-07-27T01:53:55", 
    "unfiltered": 184704, 
    "filtered": 182016, 
    "device": "openaps://cgm", 
    "rssi": 185, 
    "type": "sgv", 
    "glucose": 165
  }
]