[
  {
    "trend_arrow": "FLAT", 
    "display_time": "2016-07-28T06:58:49-07:00", 
    "noise": 1, 
    "direction": "Flat", 
    "system_time": "2016-07-28T13:48:55-07:00", 
    "sgv": 95, 
    "dateString": "2016-07-28T06:58:49-07:00", 
    "device": "openaps://cgm", 
    "unfiltered": 119280, 
    "rssi": 183, 
    "date": 1469714329000.0, 
    "filtered": 120336, 
    "type": "sgv", 
    "glucose": 95
  }, 
  {
    "trend_arrow": "FLAT", 
    "display_time": "2016-07-28T06:53:49-07:00", 
    "noise": 1, 
    "direction": "Flat", 
    "system_time": "2016-07-28T13:43:56-07:00", 
    "sgv": 96, 
    "dateString": "2016-07-28T06:53:49-07:00", 
    "device": "openaps://cgm", 
    "unfiltered": 119648, 
    "rssi": 441, 
    "date": 1469714029000.0, 
    "filtered": 122016, 
    "type": "sgv", 
    "glucose": 96
  }, 
  {
    "trend_arrow": "FLAT", 
    "display_time": "2016-07-28T06:48:49-07:00", 
    "noise": 1, 
    "direction": "Flat", 
    "system_time": "2016-07-28T13:38:55-07:00", 
    "sgv": 97, 
    "dateString": "2016-07-28T06:48:49-07:00", 
    "device": "openaps://cgm", 
    "unfiltered": 120624, 
    "rssi": 183, 
    "date": 1469713729000.0, 
    "filtered": 123616, 
    "type": "sgv", 
    "glucose": 97
  }, 
  {
    "trend_arrow": "FLAT", 
    "display_time": "2016-07-28T06:43:49-07:00", 
    "noise": 1, 
    "direction": "Flat", 
    "system_time": "2016-07-28T13:33:56-07:00", 
    "sgv": 99, 
    "dateString": "2016-07-28T06:43:49-07:00", 
    "device": "openaps://cgm", 
    "unfiltered": 122256, 
    "rssi": 438, 
    "date": 1469713429000.0, 
    "filtered": 124496, 
    "type": "sgv", 
    "glucose": 99
  }, 
  {
    "trend_arrow": "FLAT", 
    "display_time": "2016-07-28T06:38:49-07:00", 
    "noise": 1, 
    "direction": "Flat", 
    "system_time": "2016-07-28T13:28:55-07:00", 
    "sgv": 101, 
    "dateString": "2016-07-28T06:38:49-07:00", 
    "device": "openaps://cgm", 
    "unfiltered": 124160, 
    "rssi": 186, 
    "date": 1469713129000.0, 
    "filtered": 124656, 
    "type": "sgv", 
    "glucose": 101
  }, 
  {
    "trend_arrow": "FLAT", 
    "display_time": "2016-07-28T06:33:49-07:00", 
    "noise": 1, 
    "direction": "Flat", 
    "system_time": "2016-07-28T13:23:55-07:00", 
    "sgv": 102, 
    "dateString": "2016-07-28T06:33:49-07:00", 
    "device": "openaps://cgm", 
    "unfiltered": 125472, 
    "rssi": 186, 
    "date": 1469712829000.0, 
    "filtered": 124640, 
    "type": "sgv", 
    "glucose": 102
  }
]