[
  {
    "trend_arrow": "FLAT", 
    "display_time": "2016-07-31T14:10:59-07:00", 
    "noise": 1, 
    "direction": "Flat", 
    "system_time": "2016-07-31T20:06:24-07:00", 
    "sgv": 73, 
    "dateString": "2016-07-31T14:10:59-07:00", 
    "device": "openaps://cgm", 
    "unfiltered": 94816, 
    "rssi": 186, 
    "date": 1469999459000.0, 
    "filtered": 90576, 
    "type": "sgv", 
    "glucose": 73
  }, 
  {
    "trend_arrow": "FLAT", 
    "display_time": "2016-07-31T14:05:59-07:00", 
    "noise": 1, 
    "direction": "Flat", 
    "system_time": "2016-07-31T20:01:24-07:00", 
    "sgv": 71, 
    "dateString": "2016-07-31T14:05:59-07:00", 
    "device": "openaps://cgm", 
    "unfiltered": 92848, 
    "rssi": 183, 
    "date": 1469999159000.0, 
    "filtered": 89648, 
    "type": "sgv", 
    "glucose": 71
  }, 
  {
    "trend_arrow": "FLAT", 
    "display_time": "2016-07-31T14:00:59-07:00", 
    "noise": 1, 
    "direction": "Flat", 
    "system_time": "2016-07-31T19:56:24-07:00", 
    "sgv": 66, 
    "dateString": "2016-07-31T14:00:59-07:00", 
    "device": "openaps://cgm", 
    "unfiltered": 88064, 
    "rssi": 186, 
    "date": 1469998859000.0, 
    "filtered": 90032, 
    "type": "sgv", 
    "glucose": 66
  }, 
  {
    "trend_arrow": "FLAT", 
    "display_time": "2016-07-31T13:55:59-07:00", 
    "noise": 1, 
    "direction": "Flat", 
    "system_time": "2016-07-31T19:51:24-07:00", 
    "sgv": 68, 
    "dateString": "2016-07-31T13:55:59-07:00", 
    "device": "openaps://cgm", 
    "unfiltered": 90400, 
    "rssi": 184, 
    "date": 1469998559000.0, 
    "filtered": 91920, 
    "type": "sgv", 
    "glucose": 68
  }, 
  {
    "trend_arrow": "FLAT", 
    "display_time": "2016-07-31T13:50:59-07:00", 
    "noise": 1, 
    "direction": "Flat", 
    "system_time": "2016-07-31T19:46:24-07:00", 
    "sgv": 70, 
    "dateString": "2016-07-31T13:50:59-07:00", 
    "device": "openaps://cgm", 
    "unfiltered": 92160, 
    "rssi": 187, 
    "date": 1469998259000.0, 
    "filtered": 95232, 
    "type": "sgv", 
    "glucose": 70
  }, 
  {
    "trend_arrow": "45_DOWN", 
    "display_time": "2016-07-31T13:45:59-07:00", 
    "noise": 1, 
    "direction": "FortyFiveDown", 
    "system_time": "2016-07-31T19:41:24-07:00", 
    "sgv": 70, 
    "dateString": "2016-07-31T13:45:59-07:00", 
    "device": "openaps://cgm", 
    "unfiltered": 91712, 
    "rssi": 175, 
    "date": 1469997959000.0, 
    "filtered": 99696, 
    "type": "sgv", 
    "glucose": 70
  }
]