[
  {
    "trend_arrow": "45_UP", 
    "display_time": "2016-07-26T17:43:57-07:00", 
    "noise": 1, 
    "direction": "FortyFiveUp", 
    "system_time": "2016-07-27T00:34:04-07:00", 
    "sgv": 158, 
    "dateString": "2016-07-26T17:43:57-07:00", 
    "device": "openaps://cgm", 
    "unfiltered": 178112, 
    "rssi": 446, 
    "date": 1469580237000.0, 
    "filtered": 172576, 
    "type": "sgv", 
    "glucose": 158
  }, 
  {
    "trend_arrow": "45_UP", 
    "display_time": "2016-07-26T17:38:57-07:00", 
    "noise": 1, 
    "direction": "FortyFiveUp", 
    "system_time": "2016-07-27T00:29:03-07:00", 
    "sgv": 156, 
    "dateString": "2016-07-26T17:38:57-07:00", 
    "device": "openaps://cgm", 
    "unfiltered": 175936, 
    "rssi": 198, 
    "date": 1469579937000.0, 
    "filtered": 168000, 
    "type": "sgv", 
    "glucose": 156
  }, 
  {
    "trend_arrow": "45_UP", 
    "display_time": "2016-07-26T17:33:57-07:00", 
    "noise": 1, 
    "direction": "FortyFiveUp", 
    "system_time": "2016-07-27T00:24:03-07:00", 
    "sgv": 150, 
    "dateString": "2016-07-26T17:33:57-07:00", 
    "device": "openaps://cgm", 
    "unfiltered": 170400, 
    "rssi": 190, 
    "date": 1469579637000.0, 
    "filtered": 162432, 
    "type": "sgv", 
    "glucose": 150
  }, 
  {
    "trend_arrow": "45_UP", 
    "display_time": "2016-07-26T17:28:57-07:00", 
    "noise": 1, 
    "direction": "FortyFiveUp", 
    "system_time": "2016-07-27T00:19:03-07:00", 
    "sgv": 143, 
    "dateString": "2016-07-26T17:28:57-07:00", 
    "device": "openaps://cgm", 
    "unfiltered": 164576, 
    "rssi": 199, 
    "date": 1469579337000.0, 
    "filtered": 154400, 
    "type": "sgv", 
    "glucose": 143
  }, 
  {
    "trend_arrow": "SINGLE_UP", 
    "display_time": "2016-07-26T17:23:57-07:00", 
    "noise": 1, 
    "direction": "SingleUp", 
    "system_time": "2016-07-27T00:14:03-07:00", 
    "sgv": 135, 
    "dateString": "2016-07-26T17:23:57-07:00", 
    "device": "openaps://cgm", 
    "unfiltered": 157056, 
    "rssi": 194, 
    "date": 1469579037000.0, 
    "filtered": 142944, 
    "type": "sgv", 
    "glucose": 135
  }, 
  {
    "trend_arrow": "SINGLE_UP", 
    "display_time": "2016-07-26T17:18:57-07:00", 
    "noise": 1, 
    "direction": "SingleUp", 
    "system_time": "2016-07-27T00:09:03-07:00", 
    "sgv": 127, 
    "dateString": "2016-07-26T17:18:57-07:00", 
    "device": "openaps://cgm", 
    "unfiltered": 150304, 
    "rssi": 203, 
    "date": 1469578737000.0, 
    "filtered": 129808, 
    "type": "sgv", 
    "glucose": 127
  }
]