[
  {
    "trend_arrow": "45_DOWN", 
    "system_time": "2016-07-28T19:08:54", 
    "noise": 1, 
    "direction": "FortyFiveDown", 
    "sgv": 135, 
    "display_time": "2016-07-28T12:18:48", 
    "date": 1469733528000.0, 
    "dateString": "2016-07-28T12:18:48", 
    "unfiltered": 155040, 
    "filtered": 161920, 
    "device": "openaps://cgm", 
    "rssi": 204, 
    "type": "sgv", 
    "glucose": 135
  }, 
  {
    "trend_arrow": "45_DOWN", 
    "system_time": "2016-07-28T19:03:54", 
    "noise": 1, 
    "direction": "FortyFiveDown", 
    "sgv": 139, 
    "display_time": "2016-07-28T12:13:48", 
    "date": 1469733228000.0, 
    "dateString": "2016-07-28T12:13:48", 
    "unfiltered": 158720, 
    "filtered": 167360, 
    "device": "openaps://cgm", 
    "rssi": 202, 
    "type": "sgv", 
    "glucose": 139
  }, 
  {
    "trend_arrow": "45_DOWN", 
    "system_time": "2016-07-28T18:58:54", 
    "noise": 1, 
    "direction": "FortyFiveDown", 
    "sgv": 145, 
    "display_time": "2016-07-28T12:08:48", 
    "date": 1469732928000.0, 
    "dateString": "2016-07-28T12:08:48", 
    "unfiltered": 164576, 
    "filtered": 172960, 
    "device": "openaps://cgm", 
    "rssi": 179, 
    "type": "sgv", 
    "glucose": 145
  }, 
  {
    "trend_arrow": "45_DOWN", 
    "system_time": "2016-07-28T18:53:54", 
    "noise": 1, 
    "direction": "FortyFiveDown", 
    "sgv": 151, 
    "display_time": "2016-07-28T12:03:48", 
    "date": 1469732628000.0, 
    "dateString": "2016-07-28T12:03:48", 
    "unfiltered": 169856, 
    "filtered": 178464, 
    "device": "openaps://cgm", 
    "rssi": 205, 
    "type": "sgv", 
    "glucose": 151
  }, 
  {
    "trend_arrow": "45_DOWN", 
    "system_time": "2016-07-28T18:48:54", 
    "noise": 1, 
    "direction": "FortyFiveDown", 
    "sgv": 157, 
    "display_time": "2016-07-28T11:58:48", 
    "date": 1469732328000.0, 
    "dateString": "2016-07-28T11:58:48", 
    "unfiltered": 175392, 
    "filtered": 183872, 
    "device": "openaps://cgm", 
    "rssi": 193, 
    "type": "sgv", 
    "glucose": 157
  }, 
  {
    "trend_arrow": "FLAT", 
    "system_time": "2016-07-28T18:43:55", 
    "noise": 1, 
    "direction": "Flat", 
    "sgv": 164, 
    "display_time": "2016-07-28T11:53:48", 
    "date": 1469732028000.0, 
    "dateString": "2016-07-28T11:53:48", 
    "unfiltered": 181600, 
    "filtered": 188736, 
    "device": "openaps://cgm", 
    "rssi": 444, 
    "type": "sgv", 
    "glucose": 164
  }
]